setup.cfg
setup.py
openaq/__init__.py
openaq/decorators.py
openaq/exceptions.py
openaq/utils.py
openaq/viz.py
py_openaq.egg-info/PKG-INFO
py_openaq.egg-info/SOURCES.txt
py_openaq.egg-info/dependency_links.txt
py_openaq.egg-info/top_level.txt