Metadata-Version: 1.1
Name: py-openaq
Version: 1.1.0
Summary: Python wrapper for the OpenAQ API
Home-page: https://github.com/dhhagan/py-openaq
Author: David H Hagan
Author-email: david@davidhhagan.com
License: MIT
Keywords: OpenAQ,MIT,Air Quality
Platform: UNKNOWN
Classifier: Development Status :: 3 - Alpha
Classifier: Operating System :: OS Independent
Classifier: Intended Audience :: Science/Research
Classifier: Intended Audience :: Developers
Classifier: Intended Audience :: Education
Classifier: Programming Language :: Python :: 2.7
Classifier: Programming Language :: Python :: 3.3
Classifier: Programming Language :: Python :: 3.4
Classifier: Programming Language :: Python :: 3.5
Classifier: Programming Language :: Python :: 3.6
Classifier: Topic :: Scientific/Engineering :: Atmospheric Science
Classifier: Topic :: Software Development
Classifier: Topic :: Software Development :: Libraries :: Python Modules
